fast_gauss/__init__.py
fast_gauss/base_utils.py
fast_gauss/console_utils.py
fast_gauss/cuda_utils.py
fast_gauss/data_utils.py
fast_gauss/egl_utils.py
fast_gauss/gaussian_utils.py
fast_gauss/gl_utils.py
fast_gauss/gsplat_utils.py
fast_gauss/math_utils.py
fast_gauss/sh_utils.py
fast_gauss/shaders/dsplat.frag
fast_gauss/shaders/dsplat.geom
fast_gauss/shaders/dsplat.vert
fast_gauss/shaders/gsplat.frag
fast_gauss/shaders/gsplat.geom
fast_gauss/shaders/gsplat.vert
fast_gauss-0.0.9.dist-info/METADATA
fast_gauss-0.0.9.dist-info/WHEEL
fast_gauss-0.0.9.dist-info/top_level.txt
fast_gauss-0.0.9.dist-info/RECORD
