Metadata-Version: 2.1
Name: fast_gauss
Version: 0.0.9
Summary: A geometry-shader-based, global CUDA sorted high-performance 3D Gaussian Splatting rasterizer. Can achieve a 5-10x speedup in rendering compared to the vanialla diff-gaussian-rasterization.
Author: Zhen Xu
Author-email: zhenx@zju.edu.cn
License: MIT License
Project-URL: homepage, https://github.com/dendenxu/fast-gaussian-rasterization
Requires-Python: >=3.8
Requires-Dist: torch
Requires-Dist: numpy
Requires-Dist: cuda-python
Requires-Dist: PyGLM
Requires-Dist: PyOpenGL >=3.1.7
